filetailor/__init__.py
filetailor/__main__.py
filetailor/config.py
filetailor/core/__init__.py
filetailor/core/clean.py
filetailor/core/initialize.py
filetailor/core/paths.py
filetailor/core/sync.py
filetailor/core/uninstall.py
filetailor/core/update_yaml.py
filetailor/data/__init__.py
filetailor/data/config.ini
filetailor/data/example_filetailor.yaml
filetailor/data/filetailor.yaml
filetailor/helpers/__init__.py
filetailor/helpers/cprint.py
filetailor/helpers/diff.py
filetailor/helpers/get_key_list.py
filetailor/helpers/get_option.py
filetailor/helpers/load_ini_files.py
filetailor/helpers/load_yaml.py
filetailor/helpers/okay_to_continue.py
filetailor/helpers/tailor_lines.py
filetailor-0.2.0.dist-info/LICENSE
filetailor-0.2.0.dist-info/METADATA
filetailor-0.2.0.dist-info/WHEEL
filetailor-0.2.0.dist-info/entry_points.txt
filetailor-0.2.0.dist-info/top_level.txt
filetailor-0.2.0.dist-info/RECORD
