Metadata-Version: 2.1
Name: filetailor
Version: 0.2.0
Summary: Copy and modify plain text files to a folder based on YAML to be synced between devices
Home-page: https://github.com/k4j8/filetailor
Author: Kyle Johnston
Author-email: johnstonkylew@gmail.com
Project-URL: Bug Tracker, https://github.com/k4j8/filetailor/issues
Classifier: License :: OSI Approved :: GNU General Public License v3 or later (GPLv3+)
Classifier: Natural Language :: English
Classifier: Operating System :: OS Independent
Classifier: Programming Language :: Python :: 3
Classifier: Topic :: System :: Systems Administration
Requires-Python: >=3.6
License-File: LICENSE
Requires-Dist: appdirs (>=1.4.4)
Requires-Dist: pyyaml (>=5.4.1)
Requires-Dist: ruamel.yaml (>=0.17.7)
Requires-Dist: termcolor (>=1.1.0)
